oscilloscope.py
oscilloscope-0.0.4.dist-info/LICENSE
oscilloscope-0.0.4.dist-info/METADATA
oscilloscope-0.0.4.dist-info/WHEEL
oscilloscope-0.0.4.dist-info/top_level.txt
oscilloscope-0.0.4.dist-info/RECORD
