Metadata-Version: 2.1
Name: oscilloscope
Version: 0.0.4
Summary: An oscilloscope for python that just works™
Home-page: https://github.com/devxpy/oscilloscope
Author: Dev Aggarwal
Author-email: devxpy@gmail.com
License: MIT
Platform: UNKNOWN
Classifier: License :: OSI Approved :: MIT License
Classifier: Programming Language :: Python
Classifier: Programming Language :: Python :: 3
Classifier: Programming Language :: Python :: 3.6
Classifier: Programming Language :: Python :: Implementation :: CPython
Classifier: Programming Language :: Python :: Implementation :: PyPy
Requires-Python: >=3.6.0
Requires-Dist: matplotlib
Requires-Dist: zproc (>=0.9.5)
